yemen_regions_py/__init__.py
yemen_regions_py/enums.py
yemen_regions_py/models.py
yemen_regions_py/service.py
yemen_regions_py/data/yemen-info.json
yemen_regions_py-1.0.0.dist-info/licenses/LICENSE
yemen_regions_py-1.0.0.dist-info/METADATA
yemen_regions_py-1.0.0.dist-info/WHEEL
yemen_regions_py-1.0.0.dist-info/top_level.txt
yemen_regions_py-1.0.0.dist-info/RECORD
