Metadata-Version: 2.4
Name: yemen-regions-py
Version: 1.0.0
Summary: A Python library for Yemen regions (governorates, districts, uzlahs, villages) with Arabic and English support.
Author-email: YounisDany <younis@example.com>
Maintainer-email: YounisDany <younis@example.com>
License: MIT
Project-URL: Homepage, https://github.com/YounisDany/yemen-regions-py
Project-URL: Repository, https://github.com/YounisDany/yemen-regions-py
Project-URL: Issues, https://github.com/YounisDany/yemen-regions-py/issues
Project-URL: Documentation, https://github.com/YounisDany/yemen-regions-py#readme
Keywords: yemen,regions,governorates,districts,arabic,localization
Classifier: Development Status :: 5 - Production/Stable
Classifier: Intended Audience :: Developers
Classifier: License :: OSI Approved :: MIT License
Classifier: Operating System :: OS Independent
Classifier: Programming Language :: Python :: 3
Classifier: Programming Language :: Python :: 3.8
Classifier: Programming Language :: Python :: 3.9
Classifier: Programming Language :: Python :: 3.10
Classifier: Programming Language :: Python :: 3.11
Classifier: Programming Language :: Python :: 3.12
Classifier: Topic :: Software Development :: Libraries :: Python Modules
Classifier: Topic :: Software Development :: Localization
Classifier: Topic :: Text Processing :: Linguistic
Requires-Python: >=3.8
License-File: LICENSE
Provides-Extra: dev
Requires-Dist: pytest>=7.0; extra == "dev"
Requires-Dist: pytest-cov>=4.0; extra == "dev"
Requires-Dist: black>=22.0; extra == "dev"
Requires-Dist: flake8>=5.0; extra == "dev"
Requires-Dist: mypy>=1.0; extra == "dev"
Dynamic: license-file
